./.gitignore
./Dockerfile
./LICENSE
./MANIFEST.in
./PKG-INFO
./README.md
./grummage.py
./grummage_snap.mp4
./pyproject.toml
./release.py
./snap/snapcraft.yaml
grummage-2.0.0.dist-info/METADATA
grummage-2.0.0.dist-info/WHEEL
grummage-2.0.0.dist-info/entry_points.txt
grummage-2.0.0.dist-info/licenses/LICENSE
grummage-2.0.0.dist-info/RECORD
