Metadata-Version: 2.4
Name: grummage
Version: 2.0.0
Summary: Interactive terminal frontend for Grype to view vulnerabilities.
Project-URL: Homepage, https://github.com/popey/grummage
Project-URL: Repository, https://github.com/popey/grummage
Project-URL: Issues, https://github.com/popey/grummage/issues
Project-URL: Documentation, https://github.com/popey/grummage#readme
Author-email: Alan Pope <alan@popey.com>
License: MIT License
License-File: LICENSE
Keywords: sbom,security,supply-chain,terminal,tui
Classifier: Development Status :: 4 - Beta
Classifier: Environment :: Console
Classifier: Intended Audience :: Developers
Classifier: Intended Audience :: System Administrators
Classifier: License :: OSI Approved :: MIT License
Classifier: Operating System :: OS Independent
Classifier: Programming Language :: Python :: 3
Classifier: Programming Language :: Python :: 3.8
Classifier: Programming Language :: Python :: 3.9
Classifier: Programming Language :: Python :: 3.10
Classifier: Programming Language :: Python :: 3.11
Classifier: Programming Language :: Python :: 3.12
Classifier: Topic :: Security
Classifier: Topic :: Software Development :: Quality Assurance
Classifier: Topic :: System :: Systems Administration
Classifier: Topic :: Terminals
Classifier: Topic :: Text Processing :: Markup :: XML
Requires-Python: >=3.8
Requires-Dist: textual>=0.85.0
